diffq_fixed-0.2.4.dist-info/METADATA
diffq_fixed-0.2.4.dist-info/LICENSE
diffq_fixed-0.2.4.dist-info/RECORD
diffq_fixed-0.2.4.dist-info/WHEEL
diffq_fixed-0.2.4.dist-info/top_level.txt
diffq/base.py
diffq/utils.py
diffq/__init__.py
diffq/lsq.py
diffq/ts_export.py
diffq/torch_pack.py
diffq/diffq.py
diffq/bitpack.cpython-312-x86_64-linux-gnu.so
diffq/uniform.py
