Metadata-Version: 2.1
Name: diffq-fixed
Version: 0.2.4
Summary: Differentiable quantization framework for PyTorch -- fixed for compatibility with Python 3.11+
Home-page: https://github.com/JackismyShephard/diffq
Author: Alexandre Défossez, Yossi Adi, Gabriel Synnaeve, JackismyShephard
Author-email: jackismyshephard@gmail.com
License: Creative Commons Attribution-NonCommercial 4.0 International
Classifier: Topic :: Scientific/Engineering :: Artificial Intelligence
Requires-Python: >=3.7.0
License-File: LICENSE
Requires-Dist: Cython
Requires-Dist: numpy
Requires-Dist: torch
Provides-Extra: dev
Requires-Dist: coverage; extra == "dev"
Requires-Dist: flake8; extra == "dev"
Requires-Dist: pdoc3; extra == "dev"
Requires-Dist: torchvision; extra == "dev"
